stylepy/__init__.py
stylepy/format.py
stylepy/header.py
stylepy/inline.py
stylepy/json.py
stylepy/list.py
stylepy/space_complexity.py
stylepy/table.py
stylepy/time_complexity.py
stylepy-0.8.dist-info/AUTHORS.txt
stylepy-0.8.dist-info/METADATA
stylepy-0.8.dist-info/WHEEL
stylepy-0.8.dist-info/top_level.txt
stylepy-0.8.dist-info/RECORD
