Metadata-Version: 2.1
Name: stylepy
Version: 0.8
Summary: Format CLI output like HTML.
Home-page: https://github.com/web-slate/stylepy
Author: Venkatraman.R
Author-email: ramsunvtech@gmail.com
License: MIT
Requires-Python: >=3.3
License-File: AUTHORS.txt
